tempo/__init__.py
tempo/cronoapi.py
CronoAPI-1.1.1.dist-info/METADATA
CronoAPI-1.1.1.dist-info/WHEEL
CronoAPI-1.1.1.dist-info/top_level.txt
CronoAPI-1.1.1.dist-info/RECORD
