Metadata-Version: 2.1
Name: CronoAPI
Version: 1.1.1
Summary: Biblioteca de datas e horas
Author: Sabio_
Requires-Dist: datetime
